SystemVue/Analysis.py
SystemVue/Application.py
SystemVue/DataSet.py
SystemVue/Design.py
SystemVue/Equations.py
SystemVue/Graph.py
SystemVue/GraphSeries.py
SystemVue/InterpOptions.py
SystemVue/Param.py
SystemVue/Part.py
SystemVue/SlicingOptions.py
SystemVue/Variable.py
SystemVue/Workspace.py
SystemVue/__init__.py
SystemVue-2023.0.dist-info/METADATA
SystemVue-2023.0.dist-info/WHEEL
SystemVue-2023.0.dist-info/top_level.txt
SystemVue-2023.0.dist-info/RECORD
