Metadata-Version: 2.1
Name: SystemVue
Version: 2023.0
Summary: Python package for SystemVue 2023
Classifier: Programming Language :: Python :: 3
Requires-Python: ==3.10.*
Requires-Dist: numpy
Requires-Dist: pandas
Requires-Dist: psutil
